frame2seq/Frame2seqRunner.py
frame2seq/__init__.py
frame2seq/model/Frame2seq.py
frame2seq/model/__init__.py
frame2seq/model/edge_update.py
frame2seq/openfold/__init__.py
frame2seq/openfold/config.py
frame2seq/openfold/data/__init__.py
frame2seq/openfold/data/data_modules.py
frame2seq/openfold/data/data_pipeline.py
frame2seq/openfold/data/data_transforms.py
frame2seq/openfold/data/errors.py
frame2seq/openfold/data/feature_pipeline.py
frame2seq/openfold/data/input_pipeline.py
frame2seq/openfold/data/mmcif_parsing.py
frame2seq/openfold/data/parsers.py
frame2seq/openfold/data/templates.py
frame2seq/openfold/data/tools/__init__.py
frame2seq/openfold/data/tools/hhblits.py
frame2seq/openfold/data/tools/hhsearch.py
frame2seq/openfold/data/tools/jackhmmer.py
frame2seq/openfold/data/tools/kalign.py
frame2seq/openfold/data/tools/utils.py
frame2seq/openfold/model/__init__.py
frame2seq/openfold/model/dropout.py
frame2seq/openfold/model/embedders.py
frame2seq/openfold/model/evoformer.py
frame2seq/openfold/model/heads.py
frame2seq/openfold/model/model.py
frame2seq/openfold/model/msa.py
frame2seq/openfold/model/outer_product_mean.py
frame2seq/openfold/model/pair_transition.py
frame2seq/openfold/model/primitives.py
frame2seq/openfold/model/structure_module.py
frame2seq/openfold/model/structure_module_attn_figs.py
frame2seq/openfold/model/template.py
frame2seq/openfold/model/torchscript.py
frame2seq/openfold/model/triangular_attention.py
frame2seq/openfold/model/triangular_multiplicative_update.py
frame2seq/openfold/np/__init__.py
frame2seq/openfold/np/protein.py
frame2seq/openfold/np/residue_constants.py
frame2seq/openfold/np/relax/__init__.py
frame2seq/openfold/np/relax/amber_minimize.py
frame2seq/openfold/np/relax/cleanup.py
frame2seq/openfold/np/relax/relax.py
frame2seq/openfold/np/relax/utils.py
frame2seq/openfold/resources/__init__.py
frame2seq/openfold/utils/__init__.py
frame2seq/openfold/utils/argparse.py
frame2seq/openfold/utils/callbacks.py
frf2seq2-0.1.1.dist-info/LICENSE
frf2seq2-0.1.1.dist-info/METADATA
frf2seq2-0.1.1.dist-info/WHEEL
frf2seq2-0.1.1.dist-info/top_level.txt
frf2seq2-0.1.1.dist-info/RECORD
