Metadata-Version: 2.1
Name: frf2seq2
Version: 0.1.1
Summary: frame2seq test
Home-page: https://github.com/pypa/sampleproject
Author: Deniz Akpinaroglu
Author-email: dakpinaroglu@berkeley.edu
Project-URL: Bug Tracker, https://github.com/pypa/sampleproject/issues
Classifier: Programming Language :: Python :: 3
Classifier: License :: OSI Approved :: MIT License
Classifier: Operating System :: OS Independent
Requires-Python: >=3.10
License-File: LICENSE
Requires-Dist: torch >=2.1.1
Requires-Dist: biopython >=1.82
Requires-Dist: einops >=0.7.0
Requires-Dist: pytorch-lightning >=2.1.3
Requires-Dist: scipy >=1.11.4
Requires-Dist: dm-tree >=0.1.8
Requires-Dist: pandas >=2.1.4
